dphtools/__init__.py
dphtools/_version.py
dphtools/display.py
dphtools/utils/__init__.py
dphtools/utils/beads.py
dphtools/utils/fitfuncs.py
dphtools/utils/histstats.py
dphtools/utils/lm.py
dphtools/utils/lpsvd.py
dphtools/utils/registration.py
dphtools/utils/rolling_ball.py
tests/__init__.py
tests/test_display.py
tests/test_fitfuncs.py
tests/test_utils.py
dphtools-0.0.5.dist-info/LICENSE
dphtools-0.0.5.dist-info/METADATA
dphtools-0.0.5.dist-info/WHEEL
dphtools-0.0.5.dist-info/top_level.txt
dphtools-0.0.5.dist-info/RECORD
