Metadata-Version: 2.1
Name: dphtools
Version: 0.0.5
Summary: Tools for optics and image analysis
Home-page: https://github.com/david-hoffman/dphtools
Author: David Hoffman
Author-email: dave.p.hoffman@gmail.com
License: Apache V2.0
Classifier: Development Status :: 3 - Alpha
Classifier: Programming Language :: Python :: 3
Classifier: License :: OSI Approved :: Apache Software License
Classifier: Natural Language :: English
Classifier: Operating System :: OS Independent
Classifier: Topic :: Scientific/Engineering
Requires-Python: >=3.8
License-File: LICENSE
Requires-Dist: numpy
Requires-Dist: pandas
Requires-Dist: scipy
Requires-Dist: matplotlib
Requires-Dist: scikit-image
